[ {
  "name" : "Sophia",
  "phone" : "6467689999",
  "email" : "s@user.com",
  "password" : "abc1234",
  "tickets" : [ ]
}, {
  "name" : "mike",
  "phone" : "(+22) 222-333-4444",
  "email" : "m@user.com",
  "password" : "xyz987",
  "tickets" : [ ]
}, {
  "name" : "Derek",
  "phone" : "+1 (923) 424-424",
  "email" : "d@user.com",
  "password" : "1234",
  "tickets" : [ {
    "ticketId" : 1754874976720672,
    "eventName" : "graduation",
    "price" : 4.5,
    "ageType" : "Child",
    "purchased" : true,
    "owner" : "d@user.com"
  }, {
    "ticketId" : 1754876012232146,
    "eventName" : "graduation",
    "price" : 4.5,
    "ageType" : "Child",
    "purchased" : true,
    "owner" : "d@user.com"
  }, {
    "ticketId" : 1754876012256499,
    "eventName" : "graduation",
    "price" : 4.5,
    "ageType" : "Child",
    "purchased" : true,
    "owner" : "d@user.com"
  }, {
    "ticketId" : 1754876012257322,
    "eventName" : "graduation",
    "price" : 4.5,
    "ageType" : "Child",
    "purchased" : true,
    "owner" : "d@user.com"
  }, {
    "ticketId" : 1754876012258658,
    "eventName" : "graduation",
    "price" : 4.5,
    "ageType" : "Child",
    "purchased" : true,
    "owner" : "d@user.com"
  }, {
    "ticketId" : 1754876012259666,
    "eventName" : "graduation",
    "price" : 4.5,
    "ageType" : "Child",
    "purchased" : true,
    "owner" : "d@user.com"
  }, {
    "ticketId" : 1754876012260978,
    "eventName" : "graduation",
    "price" : 4.5,
    "ageType" : "Child",
    "purchased" : true,
    "owner" : "d@user.com"
  }, {
    "ticketId" : 1754876012260836,
    "eventName" : "graduation",
    "price" : 4.5,
    "ageType" : "Child",
    "purchased" : true,
    "owner" : "d@user.com"
  }, {
    "ticketId" : 1754876012261795,
    "eventName" : "graduation",
    "price" : 4.5,
    "ageType" : "Child",
    "purchased" : true,
    "owner" : "d@user.com"
  }, {
    "ticketId" : 1754876012262560,
    "eventName" : "graduation",
    "price" : 4.5,
    "ageType" : "Child",
    "purchased" : true,
    "owner" : "d@user.com"
  }, {
    "ticketId" : 1754876012263986,
    "eventName" : "graduation",
    "price" : 4.5,
    "ageType" : "Child",
    "purchased" : true,
    "owner" : "d@user.com"
  }, {
    "ticketId" : 1754876012264143,
    "eventName" : "graduation",
    "price" : 5.0,
    "ageType" : "Adult",
    "purchased" : true,
    "owner" : "d@user.com"
  }, {
    "ticketId" : 1754876012264564,
    "eventName" : "graduation",
    "price" : 5.0,
    "ageType" : "Adult",
    "purchased" : true,
    "owner" : "d@user.com"
  }, {
    "ticketId" : 1754876012265115,
    "eventName" : "graduation",
    "price" : 5.0,
    "ageType" : "Adult",
    "purchased" : true,
    "owner" : "d@user.com"
  }, {
    "ticketId" : 1754876012266892,
    "eventName" : "graduation",
    "price" : 5.0,
    "ageType" : "Adult",
    "purchased" : true,
    "owner" : "d@user.com"
  }, {
    "ticketId" : 1754876012266249,
    "eventName" : "graduation",
    "price" : 5.0,
    "ageType" : "Adult",
    "purchased" : true,
    "owner" : "d@user.com"
  }, {
    "ticketId" : 1754876012267239,
    "eventName" : "graduation",
    "price" : 5.0,
    "ageType" : "Adult",
    "purchased" : true,
    "owner" : "d@user.com"
  }, {
    "ticketId" : 1754876012267862,
    "eventName" : "graduation",
    "price" : 5.0,
    "ageType" : "Adult",
    "purchased" : true,
    "owner" : "d@user.com"
  }, {
    "ticketId" : 1754876012268772,
    "eventName" : "graduation",
    "price" : 4.25,
    "ageType" : "Senior",
    "purchased" : true,
    "owner" : "d@user.com"
  }, {
    "ticketId" : 1754876012269301,
    "eventName" : "graduation",
    "price" : 4.25,
    "ageType" : "Senior",
    "purchased" : true,
    "owner" : "d@user.com"
  }, {
    "ticketId" : 1754876012269213,
    "eventName" : "graduation",
    "price" : 4.25,
    "ageType" : "Senior",
    "purchased" : true,
    "owner" : "d@user.com"
  }, {
    "ticketId" : 1754876012270943,
    "eventName" : "graduation",
    "price" : 4.25,
    "ageType" : "Senior",
    "purchased" : true,
    "owner" : "d@user.com"
  } ]
} ]